LICENSE.txt
MANIFEST.in
Makefile
NEWS
README.rst
setup.cfg
setup.py
smc.mw.egg-info/PKG-INFO
smc.mw.egg-info/SOURCES.txt
smc.mw.egg-info/dependency_links.txt
smc.mw.egg-info/entry_points.txt
smc.mw.egg-info/namespace_packages.txt
smc.mw.egg-info/top_level.txt
smc.mw.egg-info/zip-safe
smc/mw/__init__.py
smc/mw/edit.py
smc/mw/html.py
smc/mw/mediawiki.py
smc/mw/mw.ebnf
smc/mw/mw.py
smc/mw/mw_pre.ebnf
smc/mw/mw_pre.py
smc/mw/preprocessor.py
smc/mw/semantics.py
smc/mw/semstate.py
smc/mw/settings.py
smc/mw/tool.py
tests/Makefile
tests/mwtests.py
tests/report.py
tests/testspec.ebnf
tests/testspec.py
tests/testspec_impl.py
tests/data/funcsParserTests.txt
tests/data/parserTests.txt
tests/data/smcmwTests.txt
tests/mytidylib/__init__.py
tests/mytidylib/sink.py
tests/out/README.txt
tests/out/report-0001.dat
tests/out/report-0001.html
tests/out/report-0002.dat
tests/out/report-0002.html
tests/out/report-0003.dat
tests/out/report-0003.html
tests/static/jquery-1.10.1.min.js
tests/static/report.css