Metadata-Version: 1.1
Name: smc.mw
Version: 0.3
Summary: MediaWiki-compatible parser for Python.
Home-page: https://github.com/lambdafu/smc.mw
Author: Marcus Brinkmann
Author-email: m.brinkmann@semantics.de
License: BSD
Keywords: wiki mediawiki parser peg
Platform: UNKNOWN
Classifier: Development Status :: 3 - Alpha
Classifier: Intended Audience :: Developers
Classifier: License :: OSI Approved :: BSD License
Classifier: Natural Language :: English
Classifier: Operating System :: OS Independent
Classifier: Programming Language :: Python
Classifier: Programming Language :: Python :: 2
Classifier: Programming Language :: Python :: 2.7
Classifier: Programming Language :: Python :: 3
Classifier: Programming Language :: Python :: 3.3
Classifier: Topic :: Text Processing :: Markup
Requires: lxml
Requires: grako
